dramatiq_workflow/__init__.py
dramatiq_workflow/_barrier.py
dramatiq_workflow/_base.py
dramatiq_workflow/_constants.py
dramatiq_workflow/_helpers.py
dramatiq_workflow/_middleware.py
dramatiq_workflow/_models.py
dramatiq_workflow/_serialize.py
dramatiq_workflow/_storage.py
dramatiq_workflow/tests/__init__.py
dramatiq_workflow/tests/test_barrier.py
dramatiq_workflow/tests/test_middleware.py
dramatiq_workflow/tests/test_storage.py
dramatiq_workflow/tests/test_workflow.py
dramatiq_workflow-0.3.0.dist-info/licenses/LICENSE
dramatiq_workflow-0.3.0.dist-info/METADATA
dramatiq_workflow-0.3.0.dist-info/WHEEL
dramatiq_workflow-0.3.0.dist-info/top_level.txt
dramatiq_workflow-0.3.0.dist-info/RECORD
