Metadata-Version: 2.4
Name: dramatiq-workflow
Version: 0.3.0
Summary: A library for running workflows (chains and groups of tasks) using the Python background task processing library dramatiq.
Home-page: https://github.com/Outset-AI/dramatiq-workflow
Author: Outset
Author-email: engineering@outset.ai
Classifier: Programming Language :: Python :: 3
Classifier: License :: OSI Approved :: MIT License
Classifier: Operating System :: OS Independent
Requires-Python: >=3.10
License-File: LICENSE
Requires-Dist: dramatiq>=1.10.0
Dynamic: author
Dynamic: author-email
Dynamic: classifier
Dynamic: description
Dynamic: description-content-type
Dynamic: home-page
Dynamic: license-file
Dynamic: requires-dist
Dynamic: requires-python
Dynamic: summary
